cdk_rds_mysql_backup_lambda/__init__.py
cdk_rds_mysql_backup_lambda/py.typed
cdk_rds_mysql_backup_lambda/_jsii/__init__.py
cdk_rds_mysql_backup_lambda/_jsii/cdk-rds-mysql-backup-lambda@1.0.0.jsii.tgz
cdk_rds_mysql_backup_lambda-1.0.0.dist-info/LICENSE
cdk_rds_mysql_backup_lambda-1.0.0.dist-info/METADATA
cdk_rds_mysql_backup_lambda-1.0.0.dist-info/WHEEL
cdk_rds_mysql_backup_lambda-1.0.0.dist-info/top_level.txt
cdk_rds_mysql_backup_lambda-1.0.0.dist-info/RECORD
