Metadata-Version: 2.1
Name: cdk-rds-mysql-backup-lambda
Version: 1.0.0
Summary: A flexible AWS CDK construct for scheduled RDS MySQL backups to S3.
Home-page: https://github.com/ilkrklc/cdk-rds-mysql-backup-lambda
Author: Ilker Kilic<ilkrklc@gmail.com>
License: MIT
Project-URL: Source, https://github.com/ilkrklc/cdk-rds-mysql-backup-lambda
Platform: UNKNOWN
Classifier: Intended Audience :: Developers
Classifier: Operating System :: OS Independent
Classifier: Programming Language :: JavaScript
Classifier: Programming Language :: Python :: 3 :: Only
Classifier: Programming Language :: Python :: 3.8
Classifier: Programming Language :: Python :: 3.9
Classifier: Programming Language :: Python :: 3.10
Classifier: Programming Language :: Python :: 3.11
Classifier: Typing :: Typed
Classifier: Development Status :: 5 - Production/Stable
Classifier: License :: OSI Approved
Requires-Python: ~=3.8
License-File: LICENSE
Requires-Dist: aws-cdk-lib (==2.128.0)
Requires-Dist: constructs (<11.0.0,>=10.3.0)
Requires-Dist: jsii (<2.0.0,>=1.94.0)
Requires-Dist: publication (>=0.0.3)
Requires-Dist: typeguard (~=2.13.3)
